bilingual/__init__.py
bilingual/_version.py
bilingual/api.py
bilingual/cli.py
bilingual/config.py
bilingual/data_augmentation.py
bilingual/data_utils.py
bilingual/evaluation.py
bilingual/human_evaluation.py
bilingual/language_detection.py
bilingual/multi_input.py
bilingual/normalize.py
bilingual/onnx_converter.py
bilingual/py.typed
bilingual/server.py
bilingual/testing.py
bilingual/tokenizer.py
bilingual/transformer_models.py
bilingual/models/__init__.py
bilingual/models/bilingual-tokenizer.vocab
bilingual/models/cross_lingual_embeddings.py
bilingual/models/literary_lm.py
bilingual/models/lm.py
bilingual/models/loader.py
bilingual/models/metaphor_detector.py
bilingual/models/named_entity_recognizer.py
bilingual/models/sentiment_tone_classifier.py
bilingual/models/text_complexity_predictor.py
bilingual/models/transformer.py
bilingual/models/translate.py
bilingual/modules/__init__.py
bilingual/modules/cross_lingual_embed.py
bilingual/modules/literary_analysis.py
bilingual/modules/literary_analysis1.py
bilingual/modules/literary_lm.py
bilingual/modules/metaphor_simile_detector.py
bilingual/modules/named_entity_recognizer.py
bilingual/modules/poetic_meter.py
bilingual/modules/poetic_meter1.py
bilingual/modules/sentiment_tone_classifier.py
bilingual/modules/style_transfer_gan.py
bilingual/modules/style_transfer_gpt.py
bilingual/modules/text_complexity_predictor.py
bilingual/modules/wikipedia_lm.py
bilingual/preprocessing/text_processor.py
bilingual-1.0.0.dist-info/licenses/LICENSE
bilingual-1.0.0.dist-info/METADATA
bilingual-1.0.0.dist-info/WHEEL
bilingual-1.0.0.dist-info/entry_points.txt
bilingual-1.0.0.dist-info/top_level.txt
bilingual-1.0.0.dist-info/RECORD
