Metadata-Version: 2.4
Name: bilingual
Version: 1.0.0
Summary: High-quality Bangla and English NLP toolkit for production use
Author-email: KhulnaSoft Ltd <info@khulnasoft.com>
Maintainer-email: KhulnaSoft Ltd <info@khulnasoft.com>, Md Sulaiman <dev.sulaiman@icloud.com>
License: Apache-2.0
Project-URL: Homepage, https://github.com/kothagpt/bilingual
Project-URL: Documentation, https://bilingual.readthedocs.io
Project-URL: Repository, https://github.com/kothagpt/bilingual
Project-URL: Issues, https://github.com/kothagpt/bilingual/issues
Project-URL: Changelog, https://github.com/kothagpt/bilingual/releases
Project-URL: Source Code, https://github.com/kothagpt/bilingual
Project-URL: Bug Reports, https://github.com/kothagpt/bilingual/issues
Keywords: nlp,bangla,bengali,bilingual,multilingual,tokenization,translation,language-model,ai,machine-learning
Classifier: Development Status :: 5 - Production/Stable
Classifier: Intended Audience :: Developers
Classifier: Intended Audience :: Science/Research
Classifier: Intended Audience :: Education
Classifier: Operating System :: OS Independent
Classifier: Programming Language :: Python :: 3
Classifier: Programming Language :: Python :: 3.8
Classifier: Programming Language :: Python :: 3.9
Classifier: Programming Language :: Python :: 3.10
Classifier: Programming Language :: Python :: 3.11
Classifier: Programming Language :: Python :: 3.12
Classifier: Topic :: Scientific/Engineering :: Artificial Intelligence
Classifier: Topic :: Text Processing :: Linguistic
Classifier: Topic :: Software Development :: Libraries :: Python Modules
Requires-Python: >=3.8
License-File: LICENSE
Requires-Dist: numpy>=1.20.0
Requires-Dist: sentencepiece>=0.1.96
Requires-Dist: regex>=2021.0.0
Requires-Dist: tqdm>=4.62.0
Requires-Dist: requests>=2.26.0
Requires-Dist: fastapi>=0.100.0
Requires-Dist: uvicorn[standard]>=0.23.0
Requires-Dist: pydantic>=2.0.0
Requires-Dist: pydantic-settings>=2.0.0
Provides-Extra: torch
Requires-Dist: torch>=2.0.0; extra == "torch"
Requires-Dist: transformers>=4.30.0; extra == "torch"
Requires-Dist: accelerate>=0.20.0; extra == "torch"
Requires-Dist: peft>=0.5.0; extra == "torch"
Requires-Dist: bitsandbytes>=0.41.0; extra == "torch"
Provides-Extra: onnx
Requires-Dist: onnx>=1.14.0; extra == "onnx"
Requires-Dist: onnxruntime>=1.15.0; extra == "onnx"
Requires-Dist: optimum>=1.12.0; extra == "onnx"
Provides-Extra: monitoring
Requires-Dist: prometheus-client>=0.17.0; extra == "monitoring"
Provides-Extra: dev
Requires-Dist: pytest>=7.0.0; extra == "dev"
Requires-Dist: pytest-cov>=3.0.0; extra == "dev"
Requires-Dist: pytest-asyncio>=0.21.0; extra == "dev"
Requires-Dist: black>=22.0.0; extra == "dev"
Requires-Dist: isort>=5.10.0; extra == "dev"
Requires-Dist: flake8>=4.0.0; extra == "dev"
Requires-Dist: mypy>=0.950; extra == "dev"
Requires-Dist: pre-commit>=2.17.0; extra == "dev"
Provides-Extra: docs
Requires-Dist: mkdocs>=1.5.0; extra == "docs"
Requires-Dist: mkdocs-material>=9.0.0; extra == "docs"
Requires-Dist: mkdocs-i18n>=0.1.0; extra == "docs"
Requires-Dist: mkdocstrings[python]>=0.20.0; extra == "docs"
Provides-Extra: all
Requires-Dist: bilingual[dev,docs,monitoring,onnx,torch]; extra == "all"
Dynamic: license-file
